cipher_easy/__init__.py
cipher_easy/aes.py
cipher_easy/rsa.py
cipher_easy-0.0.1.dist-info/METADATA
cipher_easy-0.0.1.dist-info/WHEEL
cipher_easy-0.0.1.dist-info/top_level.txt
cipher_easy-0.0.1.dist-info/RECORD
